honeybee_schema/__init__.py
honeybee_schema/__main__.py
honeybee_schema/_base.py
honeybee_schema/altnumber.py
honeybee_schema/boundarycondition.py
honeybee_schema/cli.py
honeybee_schema/comparison.py
honeybee_schema/geometry.py
honeybee_schema/model.py
honeybee_schema/projectinfo.py
honeybee_schema/validation.py
honeybee_schema/doe2/__init__.py
honeybee_schema/doe2/properties.py
honeybee_schema/energy/__init__.py
honeybee_schema/energy/_base.py
honeybee_schema/energy/construction.py
honeybee_schema/energy/constructionset.py
honeybee_schema/energy/daylight.py
honeybee_schema/energy/designday.py
honeybee_schema/energy/generator.py
honeybee_schema/energy/global_constructionset.py
honeybee_schema/energy/internalmass.py
honeybee_schema/energy/load.py
honeybee_schema/energy/material.py
honeybee_schema/energy/programtype.py
honeybee_schema/energy/properties.py
honeybee_schema/energy/schedule.py
honeybee_schema/energy/shw.py
honeybee_schema/energy/simulation.py
honeybee_schema/energy/ventcool.py
honeybee_schema/energy/hvac/__init__.py
honeybee_schema/energy/hvac/_template.py
honeybee_schema/energy/hvac/allair.py
honeybee_schema/energy/hvac/detailed.py
honeybee_schema/energy/hvac/doas.py
honeybee_schema/energy/hvac/heatcool.py
honeybee_schema/energy/hvac/idealair.py
honeybee_schema/radiance/__init__.py
honeybee_schema/radiance/_base.py
honeybee_schema/radiance/asset.py
honeybee_schema/radiance/global_modifierset.py
honeybee_schema/radiance/modifier.py
honeybee_schema/radiance/modifierset.py
honeybee_schema/radiance/properties.py
honeybee_schema/radiance/state.py
honeybee_schema/updater/__init__.py
honeybee_schema/updater/version_1_39_12.py
honeybee_schema/updater/version_1_40_1.py
honeybee_schema/updater/version_1_43_1.py
honeybee_schema/updater/version_1_43_2.py
honeybee_schema/updater/version_1_43_5.py
honeybee_schema-1.59.1.dist-info/licenses/LICENSE
honeybee_schema-1.59.1.dist-info/METADATA
honeybee_schema-1.59.1.dist-info/WHEEL
honeybee_schema-1.59.1.dist-info/entry_points.txt
honeybee_schema-1.59.1.dist-info/top_level.txt
honeybee_schema-1.59.1.dist-info/RECORD
