Metadata-Version: 2.4
Name: honeybee-schema
Version: 1.59.1
Summary: Honeybee Data-Model Objects
Home-page: https://github.com/ladybug-tools-in2/honeybee-schema
Author: Ladybug Tools
Author-email: info@ladybug.tools
License: BSD-3-Clause
Classifier: Programming Language :: Python :: 3.7
Classifier: Programming Language :: Python :: 3.8
Classifier: Programming Language :: Python :: 3.9
Classifier: Programming Language :: Python :: 3.10
Classifier: Programming Language :: Python :: 3.11
Classifier: Programming Language :: Python :: 3.12
Classifier: Programming Language :: Python :: Implementation :: CPython
Classifier: Operating System :: OS Independent
License-File: LICENSE
Requires-Dist: pydantic-openapi-helper>=0.2.10
Requires-Dist: honeybee-standards==2.0.7
Provides-Extra: cli
Requires-Dist: click>=7.1.2; extra == "cli"
Dynamic: author
Dynamic: author-email
Dynamic: classifier
Dynamic: description
Dynamic: description-content-type
Dynamic: home-page
Dynamic: license
Dynamic: license-file
Dynamic: provides-extra
Dynamic: requires-dist
Dynamic: summary
